LICENSE.txt
MANIFEST.in
README.rst
setup.cfg
setup.py
./cmmpy/__init__.py
./cmmpy/cmm.py
./cmmpy/tools.py
cmmpy/__init__.py
cmmpy/cmm.py
cmmpy/tools.py
cmmpy.egg-info/PKG-INFO
cmmpy.egg-info/SOURCES.txt
cmmpy.egg-info/dependency_links.txt
cmmpy.egg-info/requires.txt
cmmpy.egg-info/top_level.txt
tools/create_data.py
tools/head.txt
tools/median_grad.py