Metadata-Version: 2.1
Name: cmmpy
Version: 0.1.3
Summary: Implementation of the Comparison Model Method
Home-page: https://bitbucket.org/alecomunian/cmmpy
Author: Alessandro Comunian
Author-email: alessandro.comunian@unimi.it
License: UNKNOWN
Project-URL: Documentation, https://cmmpy.readthedocs.io/en/latest/index.html
Project-URL: Source, https://bitbucket.org/alecomunian/cmmpy
Keywords: hydrogelogy,modelling,inverse problem,direct inverse problem,modflow,flopy
Platform: UNKNOWN
Classifier: Programming Language :: Python :: 3
Classifier: License :: OSI Approved :: GNU General Public License v3 or later (GPLv3+)
Classifier: Operating System :: OS Independent
Classifier: Development Status :: 4 - Beta
Classifier: Intended Audience :: Science/Research
Classifier: Topic :: Scientific/Engineering
Requires-Python: >=3.6
